guardian_client/__init__.py
guardian_client/_version.py
guardian_client/python/__init__.py
guardian_client/python/api.py
guardian_client/python/credentials.py
guardian_client/python/guardian.py
guardian_client/python/worker_pool_client.py
guardian_client/python/worker_pool_models.py
guardian_client-2.0.1.dist-info/METADATA
guardian_client-2.0.1.dist-info/WHEEL
guardian_client-2.0.1.dist-info/entry_points.txt
guardian_client-2.0.1.dist-info/RECORD
