Metadata-Version: 2.3
Name: guardian-client
Version: 2.0.1
Summary: Python SDK for Protect AI Guardian
License: Apache-2.0
Author: ProtectAI
Author-email: community@protectai.com
Requires-Python: >=3.9,<3.13
Classifier: License :: OSI Approved :: Apache Software License
Classifier: Programming Language :: Python :: 3
Classifier: Programming Language :: Python :: 3.9
Classifier: Programming Language :: Python :: 3.10
Classifier: Programming Language :: Python :: 3.11
Classifier: Programming Language :: Python :: 3.12
Requires-Dist: click (>=8.1.7,<9.0.0)
Requires-Dist: huggingface-hub (==0.27.1)
Requires-Dist: pydantic (>=2.0.0,<3.0.0)
Requires-Dist: pyjwt (>=2.8.0,<3.0.0)
Requires-Dist: requests (>=2.32.4,<3.0.0)
Requires-Dist: setuptools (>=74.1.2,<81.0.0)
